fhirpath/__init__.py
fhirpath/__main__.py
fhirpath/constraints.py
fhirpath/enums.py
fhirpath/exceptions.py
fhirpath/fhirpath.py
fhirpath/json.py
fhirpath/model.py
fhirpath/query.py
fhirpath/search.py
fhirpath/storage.py
fhirpath/types.py
fhirpath/utils.py
fhirpath/version.py
fhirpath/connectors/__init__.py
fhirpath/connectors/connection.py
fhirpath/connectors/interfaces.py
fhirpath/connectors/url.py
fhirpath/connectors/factory/__init__.py
fhirpath/connectors/factory/es.py
fhirpath/connectors/factory/pg.py
fhirpath/dialects/__init__.py
fhirpath/dialects/base.py
fhirpath/dialects/elasticsearch.py
fhirpath/dialects/postgres.py
fhirpath/dialects/sqlalchemy.py
fhirpath/engine/__init__.py
fhirpath/engine/base.py
fhirpath/engine/fhirbase.py
fhirpath/engine/es/__init__.py
fhirpath/engine/es/mapping.py
fhirpath/fhirspec/__init__.py
fhirpath/fhirspec/downloader.py
fhirpath/fhirspec/settings.py
fhirpath/fhirspec/spec.py
fhirpath/fql/__init__.py
fhirpath/fql/expressions.py
fhirpath/fql/types.py
fhirpath/interfaces/__init__.py
fhirpath/interfaces/base.py
fhirpath/interfaces/connectors.py
fhirpath/interfaces/dialects.py
fhirpath/interfaces/engine.py
fhirpath/interfaces/fql.py
fhirpath/thirdparty/__init__.py
fhirpath/thirdparty/peewee.py
fhirpath/thirdparty/werkzeug.py
fhirpath-0.10.5.dist-info/AUTHORS.rst
fhirpath-0.10.5.dist-info/LICENSE
fhirpath-0.10.5.dist-info/METADATA
fhirpath-0.10.5.dist-info/WHEEL
fhirpath-0.10.5.dist-info/entry_points.txt
fhirpath-0.10.5.dist-info/top_level.txt
fhirpath-0.10.5.dist-info/RECORD
