Metadata-Version: 2.1
Name: fhirpath
Version: 0.10.5
Summary: FHIRPath implementation in Python.
Home-page: https://nazrul.me/fhirpath/
Author: Md Nazrul Islam
Author-email: email2nazrul@gmail.com
License: GNU General Public License v3
Project-URL: CI: Travis, https://travis-ci.org/nazrulworld/fhirpath
Project-URL: Coverage: codecov, https://codecov.io/github/nazrulworld/fhirpath
Project-URL: Docs: RTD, https://fhirpath.readthedocs.io/
Project-URL: GitHub: issues, https://github.com/nazrulworld/fhirpath/issues
Project-URL: GitHub: repo, https://github.com/nazrulworld/fhirpath
Keywords: fhirpath,HL7,FHIR,healthcare
Platform: UNKNOWN
Classifier: Development Status :: 4 - Beta
Classifier: Intended Audience :: Developers
Classifier: Intended Audience :: Healthcare Industry
Classifier: Intended Audience :: Information Technology
Classifier: License :: OSI Approved :: GNU General Public License v3 (GPLv3)
Classifier: Natural Language :: English
Classifier: Programming Language :: Python :: 3
Classifier: Programming Language :: Python :: 3 :: Only
Classifier: Programming Language :: Python :: 3.6
Classifier: Programming Language :: Python :: 3.7
Classifier: Programming Language :: Python :: 3.8
Classifier: Programming Language :: Python :: 3.9
Classifier: Typing :: Typed
Requires-Python: >=3.6
Provides-Extra: test
Provides-Extra: docs
Provides-Extra: all
